batch22/__init__.py
batch22/_version.py
batch22/eeg/__init__.py
batch22/eeg/mne/__init__.py
batch22/eeg/mne/_contexts.py
batch22/eeg/mne/_indent.py
batch22/eeg/mne/_locs.py
batch22/eeg/mne/_logging.py
batch22/eeg/mne/_summary.py
batch22/eeg/mne/_summary_EvokedComparisonGroupSummaryPlotMNE.py
batch22/eeg/mne/_summary_EvokedComparisonSummaryPlotMNE.py
batch22/eeg/mne/_valid.py
batch22/eeg/mne/_whoami.py
batch22/eeg/mne/ignore_backup__init__.py
batch22-0.1.2021.1.25.2.data/scripts/batch22-cli
batch22-0.1.2021.1.25.2.dist-info/LICENSE.txt
batch22-0.1.2021.1.25.2.dist-info/METADATA
batch22-0.1.2021.1.25.2.dist-info/WHEEL
batch22-0.1.2021.1.25.2.dist-info/top_level.txt
batch22-0.1.2021.1.25.2.dist-info/RECORD
